raspihats/__init__.py
raspihats/crc16.py
raspihats/i2c_hats/__init__.py
raspihats/i2c_hats/_base.py
raspihats/i2c_hats/_digital.py
raspihats/i2c_hats/_frame.py
raspihats/i2c_hats/robot.py
raspihats-2.4.0.dist-info/LICENSE
raspihats-2.4.0.dist-info/METADATA
raspihats-2.4.0.dist-info/WHEEL
raspihats-2.4.0.dist-info/top_level.txt
raspihats-2.4.0.dist-info/RECORD
