Metadata-Version: 2.1
Name: raspihats
Version: 2.4.0
Summary: package for controlling raspihats.com boards
Author-email: Florin COSTA <hardhat@raspihats.com>
License: The MIT License (MIT)        
Project-URL: Homepage, https://github.com/raspihats/raspihats
Project-URL: Bug Tracker, https://github.com/raspihats/raspihats/issues
Classifier: Programming Language :: Python :: 2.7
Classifier: Programming Language :: Python :: 3
Classifier: License :: OSI Approved :: MIT License
Classifier: Operating System :: OS Independent
Classifier: Development Status :: 5 - Production/Stable
Classifier: Intended Audience :: Developers
Classifier: Intended Audience :: Education
Classifier: Topic :: Software Development
Classifier: Topic :: Home Automation
Classifier: Topic :: System :: Hardware
License-File: LICENSE
Requires-Dist: smbus2
Requires-Dist: enum34 ; python_version < "3.4"
